extended_fastapi_redis_cache/__init__.py
extended_fastapi_redis_cache/cache.py
extended_fastapi_redis_cache/client.py
extended_fastapi_redis_cache/enums.py
extended_fastapi_redis_cache/key_gen.py
extended_fastapi_redis_cache/redis.py
extended_fastapi_redis_cache/types.py
extended_fastapi_redis_cache/util.py
extended_fastapi_redis_cache/version.py
extended_fastapi_redis_cache-0.1.14.dist-info/licenses/LICENSE
extended_fastapi_redis_cache-0.1.14.dist-info/METADATA
extended_fastapi_redis_cache-0.1.14.dist-info/WHEEL
extended_fastapi_redis_cache-0.1.14.dist-info/top_level.txt
extended_fastapi_redis_cache-0.1.14.dist-info/RECORD
